caffa/__init__.py
caffa/method.py
caffa/object.py
caffa/object_creator.py
caffa/restclient.py
caffa-1.7.9.dist-info/licenses/LICENSE
caffa-1.7.9.dist-info/METADATA
caffa-1.7.9.dist-info/WHEEL
caffa-1.7.9.dist-info/top_level.txt
caffa-1.7.9.dist-info/RECORD
