Metadata-Version: 2.4
Name: caffa
Version: 1.7.9
Summary: Python bindings for caffa
Author-email: Gaute Lindkvist <lindkvis@gmail.com>
Maintainer-email: Gaute Lindkvist <lindkvis@gmail.com>
License:                   GNU LESSER GENERAL PUBLIC LICENSE
Project-URL: Homepage, https://github.com/Kontur-RD/caffa-python
Project-URL: Bug Reports, https://github.com/Kontur-RD/caffa-python/issues
Project-URL: Source, https://github.com/Kontur-RD/caffa-python
Classifier: Intended Audience :: Developers
Classifier: License :: OSI Approved :: GNU Lesser General Public License v2 or later (LGPLv2+)
Classifier: Operating System :: OS Independent
Classifier: Programming Language :: Python :: 3
Requires-Python: >=3.6
License-File: LICENSE
Requires-Dist: requests
Provides-Extra: dev
Requires-Dist: pytest; extra == "dev"
Dynamic: license-file
